{
  "items": [
    {
      "id": 6076241515,
      "title": "LEGO 40761 - Smeagol & Deagol",
      "price": {
        "amount": "75.0",
        "currency_code": "EUR"
      },
      "is_visible": true,
      "discount": null,
      "brand_title": "LEGO",
      "path": "/items/6076241515-lego-40761-smeagol-deagol",
      "user": {
        "id": 36697941,
        "login": "danidk7",
        "profile_url": "https://www.vinted.fr/member/36697941-danidk7",
        "photo": {
          "id": 209270428,
          "width": 738,
          "height": 800,
          "temp_uuid": null,
          "url": "https://images1.vinted.net/t/02_009c8_Jjfj2gLcYryddBEJoN32qe3V/f800/1726732906.jpeg?s=92dbced625a61dec486d4afe889808f506294193",
          "dominant_color": "#31abc2",
          "dominant_color_opaque": "#C1E6ED",
          "thumbnails": [
            {
              "type": "thumb310",
              "url": "https://images1.vinted.net/t/02_009c8_Jjfj2gLcYryddBEJoN32qe3V/310x310/1726732906.jpeg?s=04b4dace03e5ef78b54d79f1500596b86f44e8db",
              "width": 310,
              "height": 310,
              "original_size": null
            },
            {
              "type": "thumb150",
              "url": "https://images1.vinted.net/t/02_009c8_Jjfj2gLcYryddBEJoN32qe3V/150x150/1726732906.jpeg?s=e451439407ba2cba54acad418bcc199c1f095da7",
              "width": 150,
              "height": 150,
              "original_size": null
            },
            {
              "type": "thumb100",
              "url": "https://images1.vinted.net/t/02_009c8_Jjfj2gLcYryddBEJoN32qe3V/100x100/1726732906.jpeg?s=e54aa45f2c4c0f77f5b7dbf78b39c37240d569a7",
              "width": 100,
              "height": 100,
              "original_size": null
            },
            {
              "type": "thumb50",
              "url": "https://images1.vinted.net/t/02_009c8_Jjfj2gLcYryddBEJoN32qe3V/50x50/1726732906.jpeg?s=21ee2055c81647e0eab2f397af9a53e5475d18e6",
              "width": 50,
              "height": 50,
              "original_size": null
            },
            {
              "type": "thumb20",
              "url": "https://images1.vinted.net/t/02_009c8_Jjfj2gLcYryddBEJoN32qe3V/20x20/1726732906.jpeg?s=938efabec4e2135a7eda4146d8de7772354c7719",
              "width": 20,
              "height": 20,
              "original_size": null
            }
          ],
          "is_suspicious": false,
          "orientation": null,
          "high_resolution": {
            "id": "02_009c8_Jjfj2gLcYryddBEJoN32qe3V",
            "timestamp": 1726732906,
            "orientation": null
          },
          "full_size_url": "https://images1.vinted.net/tc/02_009c8_Jjfj2gLcYryddBEJoN32qe3V/1726732906.jpeg?s=48079efac56ef9ee5656f5a65433c685094a485a",
          "is_hidden": false,
          "extra": {}
        },
        "business": false
      },
      "conversion": null,
      "url": "https://www.vinted.fr/items/6076241515-lego-40761-smeagol-deagol",
      "promoted": false,
      "photo": {
        "id": 24662745542,
        "image_no": 1,
        "width": 800,
        "height": 778,
        "dominant_color": "#4B4348",
        "dominant_color_opaque": "#C9C7C8",
        "url": "https://images1.vinted.net/t/04_00fcd_v3VmxiSjL2FMoijyotnePhu3/f800/1743623784.jpeg?s=456c42771fe28298467636744cfd5fe068d224b5",
        "is_main": true,
        "thumbnails": [
          {
            "type": "thumb70x100",
            "url": "https://images1.vinted.net/t/04_00fcd_v3VmxiSjL2FMoijyotnePhu3/70x100/1743623784.jpeg?s=15942b4998cdefc093f74eca7ac85e4fa60010d5",
            "width": 70,
            "height": 100,
            "original_size": null
          },
          {
            "type": "thumb150x210",
            "url": "https://images1.vinted.net/t/04_00fcd_v3VmxiSjL2FMoijyotnePhu3/150x210/1743623784.jpeg?s=9bfcb5062d721922df78990a3e2caaf01854c623",
            "width": 150,
            "height": 210,
            "original_size": null
          },
          {
            "type": "thumb310x430",
            "url": "https://images1.vinted.net/t/04_00fcd_v3VmxiSjL2FMoijyotnePhu3/310x430/1743623784.jpeg?s=0a6e67df123d076c5ca3c6a5b02b75957b517588",
            "width": 310,
            "height": 430,
            "original_size": null
          },
          {
            "type": "thumb428x624",
            "url": "https://images1.vinted.net/t/04_00fcd_v3VmxiSjL2FMoijyotnePhu3/f800/1743623784.jpeg?s=456c42771fe28298467636744cfd5fe068d224b5",
            "width": 428,
            "height": 416,
            "original_size": true
          },
          {
            "type": "thumb624x428",
            "url": "https://images1.vinted.net/t/04_00fcd_v3VmxiSjL2FMoijyotnePhu3/f800/1743623784.jpeg?s=456c42771fe28298467636744cfd5fe068d224b5",
            "width": 624,
            "height": 607,
            "original_size": true
          },
          {
            "type": "thumb364x428",
            "url": "https://images1.vinted.net/t/04_00fcd_v3VmxiSjL2FMoijyotnePhu3/f800/1743623784.jpeg?s=456c42771fe28298467636744cfd5fe068d224b5",
            "width": 364,
            "height": 354,
            "original_size": true
          }
        ],
        "high_resolution": {
          "id": "04_00fcd_v3VmxiSjL2FMoijyotnePhu3",
          "timestamp": 1743623784,
          "orientation": null
        },
        "is_suspicious": false,
        "full_size_url": "https://images1.vinted.net/tc/04_00fcd_v3VmxiSjL2FMoijyotnePhu3/1743623784.jpeg?s=6d8ba9c8efa00988d306b235e0ea713ff38e7fc2",
        "is_hidden": false,
        "extra": {}
      },
      "favourite_count": 61,
      "is_favourite": false,
      "badge": null,
      "service_fee": {
        "amount": "4.45",
        "currency_code": "EUR"
      },
      "total_item_price": {
        "amount": "79.45",
        "currency_code": "EUR"
      },
      "view_count": 0,
      "size_title": "",
      "content_source": "search",
      "status": "Neuf avec étiquette",
      "icon_badges": [],
      "item_box": {
        "first_line": "LEGO",
        "second_line": "Neuf avec étiquette",
        "accessibility_label": "LEGO 40761 - Smeagol & Deagol, marque: LEGO, état: Neuf avec étiquette, 75,00 €, 79,45 € Protection acheteurs incluse"
      },
      "search_tracking_params": {
        "score": 3.52560567855835,
        "matched_queries": []
      }
    },
    {
      "id": 6084431438,
      "title": "LEGO 10354 The Shire - 9 minifigures",
      "price": {
        "amount": "139.0",
        "currency_code": "EUR"
      },
      "is_visible": true,
      "discount": null,
      "brand_title": "LEGO",
      "path": "/items/6084431438-lego-10354-the-shire-9-minifigures",
      "user": {
        "id": 141705744,
        "login": "brixalley",
        "profile_url": "https://www.vinted.fr/member/141705744-brixalley",
        "photo": {
          "id": 138363693,
          "width": 800,
          "height": 800,
          "temp_uuid": null,
          "url": "https://images1.vinted.net/t/01_01dc8_pyYSvoZUrFyxix1f88jWs9Qm/f800/1682175407.jpeg?s=9e087486cfbea266e3a50907661ccd99a595ca9f",
          "dominant_color": "#31abc2",
          "dominant_color_opaque": "#C1E6ED",
          "thumbnails": [
            {
              "type": "thumb310",
              "url": "https://images1.vinted.net/t/01_01dc8_pyYSvoZUrFyxix1f88jWs9Qm/310x310/1682175407.jpeg?s=3818eeaced1c717a07a820485f58bf53038c4ae8",
              "width": 310,
              "height": 310,
              "original_size": null
            },
            {
              "type": "thumb150",
              "url": "https://images1.vinted.net/t/01_01dc8_pyYSvoZUrFyxix1f88jWs9Qm/150x150/1682175407.jpeg?s=2bce8b90f5dacf312af4f91797a9c70fd4ffda10",
              "width": 150,
              "height": 150,
              "original_size": null
            },
            {
              "type": "thumb100",
              "url": "https://images1.vinted.net/t/01_01dc8_pyYSvoZUrFyxix1f88jWs9Qm/100x100/1682175407.jpeg?s=4cf6dd719891462a8aaf4d2f176594e8021c580d",
              "width": 100,
              "height": 100,
              "original_size": null
            },
            {
              "type": "thumb50",
              "url": "https://images1.vinted.net/t/01_01dc8_pyYSvoZUrFyxix1f88jWs9Qm/50x50/1682175407.jpeg?s=4bb6d2be263f9f6148e0935b318024d3c6b8a921",
              "width": 50,
              "height": 50,
              "original_size": null
            },
            {
              "type": "thumb20",
              "url": "https://images1.vinted.net/t/01_01dc8_pyYSvoZUrFyxix1f88jWs9Qm/20x20/1682175407.jpeg?s=89fb60233230ee6e4bbd83ab8d69493fc2373486",
              "width": 20,
              "height": 20,
              "original_size": null
            }
          ],
          "is_suspicious": false,
          "orientation": null,
          "high_resolution": {
            "id": "01_01dc8_pyYSvoZUrFyxix1f88jWs9Qm",
            "timestamp": 1682175407,
            "orientation": null
          },
          "full_size_url": "https://images1.vinted.net/tc/01_01dc8_pyYSvoZUrFyxix1f88jWs9Qm/1682175407.jpeg?s=8e661f45ef0a6e09c903555239cae79f869b980e",
          "is_hidden": false,
          "extra": {}
        },
        "business": false
      },
      "conversion": null,
      "url": "https://www.vinted.fr/items/6084431438-lego-10354-the-shire-9-minifigures",
      "promoted": false,
      "photo": {
        "id": 24685596856,
        "image_no": 1,
        "width": 800,
        "height": 798,
        "dominant_color": "#7E391F",
        "dominant_color_opaque": "#D8C4BC",
        "url": "https://images1.vinted.net/t/04_008b0_hqvv2589ZcnfS8rfmGDyZRnK/f800/1743719313.jpeg?s=26ca047f8147d91aeab7d4c821ddbacb95edef30",
        "is_main": true,
        "thumbnails": [
          {
            "type": "thumb70x100",
            "url": "https://images1.vinted.net/t/04_008b0_hqvv2589ZcnfS8rfmGDyZRnK/70x100/1743719313.jpeg?s=6b45b2224cb90286123e57d23e8c770fb33150f6",
            "width": 70,
            "height": 100,
            "original_size": null
          },
          {
            "type": "thumb150x210",
            "url": "https://images1.vinted.net/t/04_008b0_hqvv2589ZcnfS8rfmGDyZRnK/150x210/1743719313.jpeg?s=2796fea68d6de552ab33ab093c212f03b6d19de4",
            "width": 150,
            "height": 210,
            "original_size": null
          },
          {
            "type": "thumb310x430",
            "url": "https://images1.vinted.net/t/04_008b0_hqvv2589ZcnfS8rfmGDyZRnK/310x430/1743719313.jpeg?s=876b63e142bd7ab5596be222370c3f2b307cc788",
            "width": 310,
            "height": 430,
            "original_size": null
          },
          {
            "type": "thumb428x624",
            "url": "https://images1.vinted.net/t/04_008b0_hqvv2589ZcnfS8rfmGDyZRnK/f800/1743719313.jpeg?s=26ca047f8147d91aeab7d4c821ddbacb95edef30",
            "width": 428,
            "height": 427,
            "original_size": true
          },
          {
            "type": "thumb624x428",
            "url": "https://images1.vinted.net/t/04_008b0_hqvv2589ZcnfS8rfmGDyZRnK/f800/1743719313.jpeg?s=26ca047f8147d91aeab7d4c821ddbacb95edef30",
            "width": 624,
            "height": 623,
            "original_size": true
          },
          {
            "type": "thumb364x428",
            "url": "https://images1.vinted.net/t/04_008b0_hqvv2589ZcnfS8rfmGDyZRnK/f800/1743719313.jpeg?s=26ca047f8147d91aeab7d4c821ddbacb95edef30",
            "width": 364,
            "height": 363,
            "original_size": true
          }
        ],
        "high_resolution": {
          "id": "04_008b0_hqvv2589ZcnfS8rfmGDyZRnK",
          "timestamp": 1743719313,
          "orientation": null
        },
        "is_suspicious": false,
        "full_size_url": "https://images1.vinted.net/tc/04_008b0_hqvv2589ZcnfS8rfmGDyZRnK/1743719313.jpeg?s=7a0e988f784589f1eecedb59b01f8919d910aa8f",
        "is_hidden": false,
        "extra": {}
      },
      "favourite_count": 6,
      "is_favourite": false,
      "badge": null,
      "service_fee": {
        "amount": "7.65",
        "currency_code": "EUR"
      },
      "total_item_price": {
        "amount": "146.65",
        "currency_code": "EUR"
      },
      "view_count": 0,
      "size_title": "Taille unique",
      "content_source": "search",
      "status": "Neuf sans étiquette",
      "icon_badges": [],
      "item_box": {
        "first_line": "LEGO",
        "second_line": "Taille unique · Neuf sans étiquette",
        "accessibility_label": "LEGO 10354 The Shire - 9 minifigures, marque: LEGO, état: Neuf sans étiquette, taille: Taille unique, 139,00 €, 146,65 € Protection acheteurs incluse"
      },
      "search_tracking_params": {
        "score": 2.423623085021973,
        "matched_queries": []
      }
    },
    {
      "id": 6086001928,
      "title": "LEGO 10354",
      "price": {
        "amount": "225.0",
        "currency_code": "EUR"
      },
      "is_visible": true,
      "discount": null,
      "brand_title": "LEGO",
      "path": "/items/6086001928-lego-10354",
      "user": {
        "id": 193992074,
        "login": "bollenstreekbricks",
        "profile_url": "https://www.vinted.fr/member/193992074-bollenstreekbricks",
        "photo": {
          "id": 184977082,
          "width": 800,
          "height": 406,
          "temp_uuid": null,
          "url": "https://images1.vinted.net/t/02_01c57_PqoBGb4XvPRDdEDif8KXEjCi/f800/1710943828.jpeg?s=5c9d1899007f9ad20102f731ab973e05410f5ba2",
          "dominant_color": "#31abc2",
          "dominant_color_opaque": "#C1E6ED",
          "thumbnails": [
            {
              "type": "thumb310",
              "url": "https://images1.vinted.net/t/02_01c57_PqoBGb4XvPRDdEDif8KXEjCi/310x310/1710943828.jpeg?s=bf6f7250bdd8821b923a8999cf60073ecedc4adb",
              "width": 310,
              "height": 310,
              "original_size": null
            },
            {
              "type": "thumb150",
              "url": "https://images1.vinted.net/t/02_01c57_PqoBGb4XvPRDdEDif8KXEjCi/150x150/1710943828.jpeg?s=c073180b2e932b618000e1dd05c5701e939fc517",
              "width": 150,
              "height": 150,
              "original_size": null
            },
            {
              "type": "thumb100",
              "url": "https://images1.vinted.net/t/02_01c57_PqoBGb4XvPRDdEDif8KXEjCi/100x100/1710943828.jpeg?s=b8b4b372e2b838a60d7d2f2b26c95ba8c653e82a",
              "width": 100,
              "height": 100,
              "original_size": null
            },
            {
              "type": "thumb50",
              "url": "https://images1.vinted.net/t/02_01c57_PqoBGb4XvPRDdEDif8KXEjCi/50x50/1710943828.jpeg?s=aafa5f1d676332198ed8fa4484b1199a3ae634c9",
              "width": 50,
              "height": 50,
              "original_size": null
            },
            {
              "type": "thumb20",
              "url": "https://images1.vinted.net/t/02_01c57_PqoBGb4XvPRDdEDif8KXEjCi/20x20/1710943828.jpeg?s=8f9358b1eb56c40019214e26261254ea418988d1",
              "width": 20,
              "height": 20,
              "original_size": null
            }
          ],
          "is_suspicious": false,
          "orientation": null,
          "high_resolution": {
            "id": "02_01c57_PqoBGb4XvPRDdEDif8KXEjCi",
            "timestamp": 1710943828,
            "orientation": null
          },
          "full_size_url": "https://images1.vinted.net/tc/02_01c57_PqoBGb4XvPRDdEDif8KXEjCi/1710943828.jpeg?s=ce5efe3b738f69946e43a7a66bc6e10b862bb502",
          "is_hidden": false,
          "extra": {}
        },
        "business": false
      },
      "conversion": null,
      "url": "https://www.vinted.fr/items/6086001928-lego-10354",
      "promoted": false,
      "photo": {
        "id": 24692222589,
        "image_no": 1,
        "width": 800,
        "height": 600,
        "dominant_color": "#748D74",
        "dominant_color_opaque": "#D5DDD5",
        "url": "https://images1.vinted.net/t/04_00d1f_bgu4VeG3dGGiCPj5MWH8x4X2/f800/1743766013.jpeg?s=68f244f390baed37aafeb3e1b87e7e69be2290a2",
        "is_main": true,
        "thumbnails": [
          {
            "type": "thumb70x100",
            "url": "https://images1.vinted.net/t/04_00d1f_bgu4VeG3dGGiCPj5MWH8x4X2/70x100/1743766013.jpeg?s=b1b142bfad7dca2ab8a5578eabc8118bd8dfc15f",
            "width": 70,
            "height": 100,
            "original_size": null
          },
          {
            "type": "thumb150x210",
            "url": "https://images1.vinted.net/t/04_00d1f_bgu4VeG3dGGiCPj5MWH8x4X2/150x210/1743766013.jpeg?s=7687e94c2056425bb514688a86172a14e0245daa",
            "width": 150,
            "height": 210,
            "original_size": null
          },
          {
            "type": "thumb310x430",
            "url": "https://images1.vinted.net/t/04_00d1f_bgu4VeG3dGGiCPj5MWH8x4X2/310x430/1743766013.jpeg?s=e5c50cb2c391bd7b6aba5b648c68747564fb03ca",
            "width": 310,
            "height": 430,
            "original_size": null
          },
          {
            "type": "thumb428x624",
            "url": "https://images1.vinted.net/t/04_00d1f_bgu4VeG3dGGiCPj5MWH8x4X2/f800/1743766013.jpeg?s=68f244f390baed37aafeb3e1b87e7e69be2290a2",
            "width": 428,
            "height": 321,
            "original_size": true
          },
          {
            "type": "thumb624x428",
            "url": "https://images1.vinted.net/t/04_00d1f_bgu4VeG3dGGiCPj5MWH8x4X2/f800/1743766013.jpeg?s=68f244f390baed37aafeb3e1b87e7e69be2290a2",
            "width": 624,
            "height": 468,
            "original_size": true
          },
          {
            "type": "thumb364x428",
            "url": "https://images1.vinted.net/t/04_00d1f_bgu4VeG3dGGiCPj5MWH8x4X2/f800/1743766013.jpeg?s=68f244f390baed37aafeb3e1b87e7e69be2290a2",
            "width": 364,
            "height": 273,
            "original_size": true
          }
        ],
        "high_resolution": {
          "id": "04_00d1f_bgu4VeG3dGGiCPj5MWH8x4X2",
          "timestamp": 1743766013,
          "orientation": null
        },
        "is_suspicious": false,
        "full_size_url": "https://images1.vinted.net/tc/04_00d1f_bgu4VeG3dGGiCPj5MWH8x4X2/1743766013.jpeg?s=bc5dcb7683f430cb813b106a60b9f1376fa819c2",
        "is_hidden": false,
        "extra": {}
      },
      "favourite_count": 5,
      "is_favourite": false,
      "badge": null,
      "service_fee": {
        "amount": "11.95",
        "currency_code": "EUR"
      },
      "total_item_price": {
        "amount": "236.95",
        "currency_code": "EUR"
      },
      "view_count": 0,
      "size_title": "Taille unique",
      "content_source": "search",
      "status": "Neuf sans étiquette",
      "icon_badges": [],
      "item_box": {
        "first_line": "LEGO",
        "second_line": "Taille unique · Neuf sans étiquette",
        "accessibility_label": "LEGO 10354, marque: LEGO, état: Neuf sans étiquette, taille: Taille unique, 225,00 €, 236,95 € Protection acheteurs incluse"
      },
      "search_tracking_params": {
        "score": 2.269008636474609,
        "matched_queries": []
      }
    },
    {
      "id": 6080797849,
      "title": "Lego LOTR 10354 - The Shire (La contea)",
      "price": {
        "amount": "230.0",
        "currency_code": "EUR"
      },
      "is_visible": true,
      "discount": null,
      "brand_title": "LEGO",
      "path": "/items/6080797849-lego-lotr-10354-the-shire-la-contea",
      "user": {
        "id": 63347909,
        "login": "real_teo",
        "profile_url": "https://www.vinted.fr/member/63347909-realteo",
        "photo": {
          "id": 195542088,
          "width": 449,
          "height": 800,
          "temp_uuid": null,
          "url": "https://images1.vinted.net/t/02_020f1_aFnRmZgdLFddUgeqhdeUpXkT/f800/1717668635.jpeg?s=67a506bcddf61437a85e02dd484099540be67ea7",
          "dominant_color": "#31abc2",
          "dominant_color_opaque": "#C1E6ED",
          "thumbnails": [
            {
              "type": "thumb310",
              "url": "https://images1.vinted.net/t/02_020f1_aFnRmZgdLFddUgeqhdeUpXkT/310x310/1717668635.jpeg?s=597b627d043d41ad522403356c42154d0f760289",
              "width": 310,
              "height": 310,
              "original_size": null
            },
            {
              "type": "thumb150",
              "url": "https://images1.vinted.net/t/02_020f1_aFnRmZgdLFddUgeqhdeUpXkT/150x150/1717668635.jpeg?s=c37f5b79da5749c707b188a6ea7976c82c6cec0b",
              "width": 150,
              "height": 150,
              "original_size": null
            },
            {
              "type": "thumb100",
              "url": "https://images1.vinted.net/t/02_020f1_aFnRmZgdLFddUgeqhdeUpXkT/100x100/1717668635.jpeg?s=7a2721926c6bc88c047f676b042ec3e548c2b80b",
              "width": 100,
              "height": 100,
              "original_size": null
            },
            {
              "type": "thumb50",
              "url": "https://images1.vinted.net/t/02_020f1_aFnRmZgdLFddUgeqhdeUpXkT/50x50/1717668635.jpeg?s=bd4f55555d7b7fabfff50ae3a9798d1b845d5adf",
              "width": 50,
              "height": 50,
              "original_size": null
            },
            {
              "type": "thumb20",
              "url": "https://images1.vinted.net/t/02_020f1_aFnRmZgdLFddUgeqhdeUpXkT/20x20/1717668635.jpeg?s=cb716376ef18417e81ace4e7a89ba626a49b609c",
              "width": 20,
              "height": 20,
              "original_size": null
            }
          ],
          "is_suspicious": false,
          "orientation": null,
          "high_resolution": {
            "id": "02_020f1_aFnRmZgdLFddUgeqhdeUpXkT",
            "timestamp": 1717668635,
            "orientation": null
          },
          "full_size_url": "https://images1.vinted.net/tc/02_020f1_aFnRmZgdLFddUgeqhdeUpXkT/1717668635.jpeg?s=548fbffd42b5a560d3c7ee97c2c3232ef024efa1",
          "is_hidden": false,
          "extra": {}
        },
        "business": false
      },
      "conversion": null,
      "url": "https://www.vinted.fr/items/6080797849-lego-lotr-10354-the-shire-la-contea",
      "promoted": false,
      "photo": {
        "id": 24670293149,
        "image_no": 1,
        "width": 640,
        "height": 475,
        "dominant_color": "#565357",
        "dominant_color_opaque": "#CCCBCD",
        "url": "https://images1.vinted.net/t/04_01995_fdhGrb3nje2zxVV8ukN8Dg2X/f800/1743676511.jpeg?s=7de39770c7103ba70d8f74445d41294bbd43b4dc",
        "is_main": true,
        "thumbnails": [
          {
            "type": "thumb70x100",
            "url": "https://images1.vinted.net/t/04_01995_fdhGrb3nje2zxVV8ukN8Dg2X/70x100/1743676511.jpeg?s=4eb63a5f063b753a8bfef96de36051fa3db8286b",
            "width": 70,
            "height": 100,
            "original_size": null
          },
          {
            "type": "thumb150x210",
            "url": "https://images1.vinted.net/t/04_01995_fdhGrb3nje2zxVV8ukN8Dg2X/150x210/1743676511.jpeg?s=9d06b6069c48b617088853f028aa75b0566d0d57",
            "width": 150,
            "height": 210,
            "original_size": null
          },
          {
            "type": "thumb310x430",
            "url": "https://images1.vinted.net/t/04_01995_fdhGrb3nje2zxVV8ukN8Dg2X/310x430/1743676511.jpeg?s=a21abe1754c7ff787eb48886c7076f8a55a428b3",
            "width": 310,
            "height": 430,
            "original_size": null
          },
          {
            "type": "thumb428x624",
            "url": "https://images1.vinted.net/t/04_01995_fdhGrb3nje2zxVV8ukN8Dg2X/f800/1743676511.jpeg?s=7de39770c7103ba70d8f74445d41294bbd43b4dc",
            "width": 428,
            "height": 317,
            "original_size": true
          },
          {
            "type": "thumb624x428",
            "url": "https://images1.vinted.net/t/04_01995_fdhGrb3nje2zxVV8ukN8Dg2X/f800/1743676511.jpeg?s=7de39770c7103ba70d8f74445d41294bbd43b4dc",
            "width": 624,
            "height": 463,
            "original_size": true
          },
          {
            "type": "thumb364x428",
            "url": "https://images1.vinted.net/t/04_01995_fdhGrb3nje2zxVV8ukN8Dg2X/f800/1743676511.jpeg?s=7de39770c7103ba70d8f74445d41294bbd43b4dc",
            "width": 364,
            "height": 270,
            "original_size": true
          }
        ],
        "high_resolution": {
          "id": "04_01995_fdhGrb3nje2zxVV8ukN8Dg2X",
          "timestamp": 1743676511,
          "orientation": 0
        },
        "is_suspicious": false,
        "full_size_url": "https://images1.vinted.net/tc/04_01995_fdhGrb3nje2zxVV8ukN8Dg2X/1743676511.jpeg?s=5ad6fe831669e8a26c9fbb07f0773557792005ad",
        "is_hidden": false,
        "extra": {}
      },
      "favourite_count": 16,
      "is_favourite": false,
      "badge": null,
      "service_fee": {
        "amount": "12.2",
        "currency_code": "EUR"
      },
      "total_item_price": {
        "amount": "242.2",
        "currency_code": "EUR"
      },
      "view_count": 0,
      "size_title": "Taille unique",
      "content_source": "search",
      "status": "Neuf avec étiquette",
      "icon_badges": [],
      "item_box": {
        "first_line": "LEGO",
        "second_line": "Taille unique · Neuf avec étiquette",
        "accessibility_label": "Lego LOTR 10354 - The Shire (La contea), marque: LEGO, état: Neuf avec étiquette, taille: Taille unique, 230,00 €, 242,20 € Protection acheteurs incluse"
      },
      "search_tracking_params": {
        "score": 2.079288482666016,
        "matched_queries": []
      }
    },
    {
      "id": 6076495799,
      "title": "Set Lego 10354, Le seigneur des anneaux, La Conté SANS Figurine",
      "price": {
        "amount": "190.0",
        "currency_code": "EUR"
      },
      "is_visible": true,
      "discount": null,
      "brand_title": "LEGO",
      "path": "/items/6076495799-set-lego-10354-le-seigneur-des-anneaux-la-conte-sans-figurine",
      "user": {
        "id": 16681586,
        "login": "mehdi_blkh",
        "profile_url": "https://www.vinted.fr/member/16681586-mehdiblkh",
        "photo": {
          "id": 9179448,
          "width": 800,
          "height": 599,
          "temp_uuid": null,
          "url": "https://images1.vinted.net/t/02_00120_ryof5ABq2FLSuiS6exADRqu1/f800/1605241094.jpeg?s=0e43fd2149ad9c0c9c9955e86eb1bcf1529697ce",
          "dominant_color": "#31abc2",
          "dominant_color_opaque": "#C1E6ED",
          "thumbnails": [
            {
              "type": "thumb310",
              "url": "https://images1.vinted.net/t/02_00120_ryof5ABq2FLSuiS6exADRqu1/310x310/1605241094.jpeg?s=ae422b93bc989f5bb41985d9536556c0df777b3e",
              "width": 310,
              "height": 310,
              "original_size": null
            },
            {
              "type": "thumb150",
              "url": "https://images1.vinted.net/t/02_00120_ryof5ABq2FLSuiS6exADRqu1/150x150/1605241094.jpeg?s=19089186ece809baa0ce3fddbc35d734076bcb0f",
              "width": 150,
              "height": 150,
              "original_size": null
            },
            {
              "type": "thumb100",
              "url": "https://images1.vinted.net/t/02_00120_ryof5ABq2FLSuiS6exADRqu1/100x100/1605241094.jpeg?s=776fbe9f055b1e38d47c79f825a9ca7949840926",
              "width": 100,
              "height": 100,
              "original_size": null
            },
            {
              "type": "thumb50",
              "url": "https://images1.vinted.net/t/02_00120_ryof5ABq2FLSuiS6exADRqu1/50x50/1605241094.jpeg?s=44a2e74266827322356bcbb5a4a17d16646969c9",
              "width": 50,
              "height": 50,
              "original_size": null
            },
            {
              "type": "thumb20",
              "url": "https://images1.vinted.net/t/02_00120_ryof5ABq2FLSuiS6exADRqu1/20x20/1605241094.jpeg?s=89a04626625fbdec9c0682c8fa7597bc627cf0cf",
              "width": 20,
              "height": 20,
              "original_size": null
            }
          ],
          "is_suspicious": false,
          "orientation": null,
          "high_resolution": {
            "id": "02_00120_ryof5ABq2FLSuiS6exADRqu1",
            "timestamp": 1605241094,
            "orientation": null
          },
          "full_size_url": "https://images1.vinted.net/tc/02_00120_ryof5ABq2FLSuiS6exADRqu1/1605241094.jpeg?s=f12d6af29e5193d7dd42bdc6784e6de02a44a7a1",
          "is_hidden": false,
          "extra": {}
        },
        "business": false
      },
      "conversion": null,
      "url": "https://www.vinted.fr/items/6076495799-set-lego-10354-le-seigneur-des-anneaux-la-conte-sans-figurine",
      "promoted": false,
      "photo": {
        "id": 24652270912,
        "image_no": 1,
        "width": 800,
        "height": 671,
        "dominant_color": "#6C7D5F",
        "dominant_color_opaque": "#D3D8CF",
        "url": "https://images1.vinted.net/t/02_00a28_2CXLu4nfE5Qn2XmUbHpdaoDe/f800/1743600792.jpeg?s=115617deb5a6901d52c95b8da1989ff765f2bd16",
        "is_main": true,
        "thumbnails": [
          {
            "type": "thumb70x100",
            "url": "https://images1.vinted.net/t/02_00a28_2CXLu4nfE5Qn2XmUbHpdaoDe/70x100/1743600792.jpeg?s=d3dbd90e5d7cc63c7b8d5d33dd3f54552291b975",
            "width": 70,
            "height": 100,
            "original_size": null
          },
          {
            "type": "thumb150x210",
            "url": "https://images1.vinted.net/t/02_00a28_2CXLu4nfE5Qn2XmUbHpdaoDe/150x210/1743600792.jpeg?s=6058a2aa67803c7425ea62c4c64f85bda5889d96",
            "width": 150,
            "height": 210,
            "original_size": null
          },
          {
            "type": "thumb310x430",
            "url": "https://images1.vinted.net/t/02_00a28_2CXLu4nfE5Qn2XmUbHpdaoDe/310x430/1743600792.jpeg?s=47698680fe413a32961ea3fdfadf97bd9b9b6278",
            "width": 310,
            "height": 430,
            "original_size": null
          },
          {
            "type": "thumb428x624",
            "url": "https://images1.vinted.net/t/02_00a28_2CXLu4nfE5Qn2XmUbHpdaoDe/f800/1743600792.jpeg?s=115617deb5a6901d52c95b8da1989ff765f2bd16",
            "width": 428,
            "height": 359,
            "original_size": true
          },
          {
            "type": "thumb624x428",
            "url": "https://images1.vinted.net/t/02_00a28_2CXLu4nfE5Qn2XmUbHpdaoDe/f800/1743600792.jpeg?s=115617deb5a6901d52c95b8da1989ff765f2bd16",
            "width": 624,
            "height": 523,
            "original_size": true
          },
          {
            "type": "thumb364x428",
            "url": "https://images1.vinted.net/t/02_00a28_2CXLu4nfE5Qn2XmUbHpdaoDe/f800/1743600792.jpeg?s=115617deb5a6901d52c95b8da1989ff765f2bd16",
            "width": 364,
            "height": 305,
            "original_size": true
          }
        ],
        "high_resolution": {
          "id": "02_00a28_2CXLu4nfE5Qn2XmUbHpdaoDe",
          "timestamp": 1743600792,
          "orientation": null
        },
        "is_suspicious": false,
        "full_size_url": "https://images1.vinted.net/tc/02_00a28_2CXLu4nfE5Qn2XmUbHpdaoDe/1743600792.jpeg?s=d33842ad5c8cb396cf5791e54a5037f470576629",
        "is_hidden": false,
        "extra": {}
      },
      "favourite_count": 15,
      "is_favourite": false,
      "badge": null,
      "service_fee": {
        "amount": "10.2",
        "currency_code": "EUR"
      },
      "total_item_price": {
        "amount": "200.2",
        "currency_code": "EUR"
      },
      "view_count": 0,
      "size_title": "Taille unique",
      "content_source": "search",
      "status": "Neuf avec étiquette",
      "icon_badges": [],
      "item_box": {
        "first_line": "LEGO",
        "second_line": "Taille unique · Neuf avec étiquette",
        "accessibility_label": "Set Lego 10354, Le seigneur des anneaux, La Conté SANS Figurine, marque: LEGO, état: Neuf avec étiquette, taille: Taille unique, 190,00 €, 200,20 € Protection acheteurs incluse"
      },
      "search_tracking_params": {
        "score": 1.754233717918396,
        "matched_queries": []
      }
    },
    {
      "id": 6080864663,
      "title": "Set Lego 10354 The Shire Seigneur des Anneaux Sans Figurines !",
      "price": {
        "amount": "180.0",
        "currency_code": "EUR"
      },
      "is_visible": true,
      "discount": null,
      "brand_title": "LEGO",
      "path": "/items/6080864663-set-lego-10354-the-shire-seigneur-des-anneaux-sans-figurines",
      "user": {
        "id": 42751499,
        "login": "nephew17",
        "profile_url": "https://www.vinted.fr/member/42751499-nephew17",
        "photo": {
          "id": 44389039,
          "width": 800,
          "height": 800,
          "temp_uuid": null,
          "url": "https://images1.vinted.net/t/02_00035_MNvwHu5G4z6z5BfTgeGdMzTy/f800/1609772991.jpeg?s=019f7c28f13da61666434ebf6ecdbbe7bbb1a943",
          "dominant_color": "#31abc2",
          "dominant_color_opaque": "#C1E6ED",
          "thumbnails": [
            {
              "type": "thumb310",
              "url": "https://images1.vinted.net/t/02_00035_MNvwHu5G4z6z5BfTgeGdMzTy/310x310/1609772991.jpeg?s=dd3930fff12c2d92e3dccc29b838356f6836c1c5",
              "width": 310,
              "height": 310,
              "original_size": null
            },
            {
              "type": "thumb150",
              "url": "https://images1.vinted.net/t/02_00035_MNvwHu5G4z6z5BfTgeGdMzTy/150x150/1609772991.jpeg?s=248d5ba3cf862f40540099f563ece06f1b50439e",
              "width": 150,
              "height": 150,
              "original_size": null
            },
            {
              "type": "thumb100",
              "url": "https://images1.vinted.net/t/02_00035_MNvwHu5G4z6z5BfTgeGdMzTy/100x100/1609772991.jpeg?s=140a726da3eb823e8618f7140e4c867e2eecb91a",
              "width": 100,
              "height": 100,
              "original_size": null
            },
            {
              "type": "thumb50",
              "url": "https://images1.vinted.net/t/02_00035_MNvwHu5G4z6z5BfTgeGdMzTy/50x50/1609772991.jpeg?s=e073e9e7d7c5c6dd8a74445025e009f1cee31247",
              "width": 50,
              "height": 50,
              "original_size": null
            },
            {
              "type": "thumb20",
              "url": "https://images1.vinted.net/t/02_00035_MNvwHu5G4z6z5BfTgeGdMzTy/20x20/1609772991.jpeg?s=eb0aacbca8825e59205ac1852cc9041e8cf919da",
              "width": 20,
              "height": 20,
              "original_size": null
            }
          ],
          "is_suspicious": false,
          "orientation": null,
          "high_resolution": {
            "id": "02_00035_MNvwHu5G4z6z5BfTgeGdMzTy",
            "timestamp": 1609772991,
            "orientation": null
          },
          "full_size_url": "https://images1.vinted.net/tc/02_00035_MNvwHu5G4z6z5BfTgeGdMzTy/1609772991.jpeg?s=5b124e9947fba7b0b9d413ac1b9391f7a87e19be",
          "is_hidden": false,
          "extra": {}
        },
        "business": false
      },
      "conversion": null,
      "url": "https://www.vinted.fr/items/6080864663-set-lego-10354-the-shire-seigneur-des-anneaux-sans-figurines",
      "promoted": false,
      "photo": {
        "id": 24670572328,
        "image_no": 1,
        "width": 800,
        "height": 580,
        "dominant_color": "#5A8B82",
        "dominant_color_opaque": "#CEDCDA",
        "url": "https://images1.vinted.net/t/03_0032a_g2AvVstF5fg92Y7cgh7VtEFe/f800/1743677260.jpeg?s=ee1f9a7ac9422737272b29c0326be15b74427b5e",
        "is_main": true,
        "thumbnails": [
          {
            "type": "thumb70x100",
            "url": "https://images1.vinted.net/t/03_0032a_g2AvVstF5fg92Y7cgh7VtEFe/70x100/1743677260.jpeg?s=74eafeea02b4caf3c91779c7b62a911e3d534a0a",
            "width": 70,
            "height": 100,
            "original_size": null
          },
          {
            "type": "thumb150x210",
            "url": "https://images1.vinted.net/t/03_0032a_g2AvVstF5fg92Y7cgh7VtEFe/150x210/1743677260.jpeg?s=6a5c7295d67755dee4f2f316abe9836a170983eb",
            "width": 150,
            "height": 210,
            "original_size": null
          },
          {
            "type": "thumb310x430",
            "url": "https://images1.vinted.net/t/03_0032a_g2AvVstF5fg92Y7cgh7VtEFe/310x430/1743677260.jpeg?s=ffaccb7d53e833e44d8284d6ee8a3c7c62313206",
            "width": 310,
            "height": 430,
            "original_size": null
          },
          {
            "type": "thumb428x624",
            "url": "https://images1.vinted.net/t/03_0032a_g2AvVstF5fg92Y7cgh7VtEFe/f800/1743677260.jpeg?s=ee1f9a7ac9422737272b29c0326be15b74427b5e",
            "width": 428,
            "height": 310,
            "original_size": true
          },
          {
            "type": "thumb624x428",
            "url": "https://images1.vinted.net/t/03_0032a_g2AvVstF5fg92Y7cgh7VtEFe/f800/1743677260.jpeg?s=ee1f9a7ac9422737272b29c0326be15b74427b5e",
            "width": 624,
            "height": 452,
            "original_size": true
          },
          {
            "type": "thumb364x428",
            "url": "https://images1.vinted.net/t/03_0032a_g2AvVstF5fg92Y7cgh7VtEFe/f800/1743677260.jpeg?s=ee1f9a7ac9422737272b29c0326be15b74427b5e",
            "width": 364,
            "height": 263,
            "original_size": true
          }
        ],
        "high_resolution": {
          "id": "03_0032a_g2AvVstF5fg92Y7cgh7VtEFe",
          "timestamp": 1743677260,
          "orientation": null
        },
        "is_suspicious": false,
        "full_size_url": "https://images1.vinted.net/tc/03_0032a_g2AvVstF5fg92Y7cgh7VtEFe/1743677260.jpeg?s=66206c93489fa83c1b5b71aa1305527e7873e8d5",
        "is_hidden": false,
        "extra": {}
      },
      "favourite_count": 16,
      "is_favourite": false,
      "badge": null,
      "service_fee": {
        "amount": "9.7",
        "currency_code": "EUR"
      },
      "total_item_price": {
        "amount": "189.7",
        "currency_code": "EUR"
      },
      "view_count": 0,
      "size_title": "Prématuré, jusqu'à 44cm",
      "content_source": "search",
      "status": "Neuf sans étiquette",
      "icon_badges": [],
      "item_box": {
        "first_line": "LEGO",
        "second_line": "Prématuré, jusqu'à 44cm · Neuf sans étiquette",
        "accessibility_label": "Set Lego 10354 The Shire Seigneur des Anneaux Sans Figurines !, marque: LEGO, état: Neuf sans étiquette, taille: Prématuré, jusqu'à 44cm, 180,00 €, 189,70 € Protection acheteurs incluse"
      },
      "search_tracking_params": {
        "score": 1.750436663627625,
        "matched_queries": []
      }
    },
    {
      "id": 6074769018,
      "title": "Lego seigneur des anneaux",
      "price": {
        "amount": "370.0",
        "currency_code": "EUR"
      },
      "is_visible": true,
      "discount": null,
      "brand_title": "LEGO",
      "path": "/items/6074769018-lego-seigneur-des-anneaux",
      "user": {
        "id": 40363377,
        "login": "xavier1040",
        "profile_url": "https://www.vinted.fr/member/40363377-xavier1040",
        "photo": {
          "id": 106396675,
          "width": 600,
          "height": 800,
          "temp_uuid": null,
          "url": "https://images1.vinted.net/t/02_004d6_Q12RCZBLWGwVaRZzCjvZxeoP/f800/1663165277.jpeg?s=239a4fcb4fbba1f415dd613fc299a8f5739c540d",
          "dominant_color": "#31abc2",
          "dominant_color_opaque": "#C1E6ED",
          "thumbnails": [
            {
              "type": "thumb310",
              "url": "https://images1.vinted.net/t/02_004d6_Q12RCZBLWGwVaRZzCjvZxeoP/310x310/1663165277.jpeg?s=dd02d848fdec289a5426edff611cb01d96578f87",
              "width": 310,
              "height": 310,
              "original_size": null
            },
            {
              "type": "thumb150",
              "url": "https://images1.vinted.net/t/02_004d6_Q12RCZBLWGwVaRZzCjvZxeoP/150x150/1663165277.jpeg?s=808fa51e5185557ffc760f1205f2770dff795d28",
              "width": 150,
              "height": 150,
              "original_size": null
            },
            {
              "type": "thumb100",
              "url": "https://images1.vinted.net/t/02_004d6_Q12RCZBLWGwVaRZzCjvZxeoP/100x100/1663165277.jpeg?s=a7caee233ac427b93b72505934cd5c595ce76aeb",
              "width": 100,
              "height": 100,
              "original_size": null
            },
            {
              "type": "thumb50",
              "url": "https://images1.vinted.net/t/02_004d6_Q12RCZBLWGwVaRZzCjvZxeoP/50x50/1663165277.jpeg?s=356f22f1293ac6061748ba6d30c9d4fa384bab66",
              "width": 50,
              "height": 50,
              "original_size": null
            },
            {
              "type": "thumb20",
              "url": "https://images1.vinted.net/t/02_004d6_Q12RCZBLWGwVaRZzCjvZxeoP/20x20/1663165277.jpeg?s=67c52f4d6e0b46f0a7d8197a067d7283876d2ce8",
              "width": 20,
              "height": 20,
              "original_size": null
            }
          ],
          "is_suspicious": false,
          "orientation": null,
          "high_resolution": {
            "id": "02_004d6_Q12RCZBLWGwVaRZzCjvZxeoP",
            "timestamp": 1663165277,
            "orientation": null
          },
          "full_size_url": "https://images1.vinted.net/tc/02_004d6_Q12RCZBLWGwVaRZzCjvZxeoP/1663165277.jpeg?s=42f7fffd3ec26624a3138576f30035625b17f482",
          "is_hidden": false,
          "extra": {}
        },
        "business": false
      },
      "conversion": null,
      "url": "https://www.vinted.fr/items/6074769018-lego-seigneur-des-anneaux",
      "promoted": false,
      "photo": {
        "id": 24645118195,
        "image_no": 1,
        "width": 600,
        "height": 800,
        "dominant_color": "#433E2B",
        "dominant_color_opaque": "#C7C5BF",
        "url": "https://images1.vinted.net/t/04_014b4_EF8wWXjzYV4HMk4QMa6zhEMb/f800/1743583808.jpeg?s=b70e4aed4f7febc5781988b0c02e8b53a9d06dab",
        "is_main": true,
        "thumbnails": [
          {
            "type": "thumb70x100",
            "url": "https://images1.vinted.net/t/04_014b4_EF8wWXjzYV4HMk4QMa6zhEMb/70x100/1743583808.jpeg?s=5ec80cbafa18960832570d75f34fc5c54a0cf435",
            "width": 70,
            "height": 100,
            "original_size": null
          },
          {
            "type": "thumb150x210",
            "url": "https://images1.vinted.net/t/04_014b4_EF8wWXjzYV4HMk4QMa6zhEMb/150x210/1743583808.jpeg?s=724207609a08f849feb02a3ca1c1ea13a4d552e4",
            "width": 150,
            "height": 210,
            "original_size": null
          },
          {
            "type": "thumb310x430",
            "url": "https://images1.vinted.net/t/04_014b4_EF8wWXjzYV4HMk4QMa6zhEMb/310x430/1743583808.jpeg?s=4536600d851490dd04bcaa7253482e95e9be53f0",
            "width": 310,
            "height": 430,
            "original_size": null
          },
          {
            "type": "thumb428x624",
            "url": "https://images1.vinted.net/t/04_014b4_EF8wWXjzYV4HMk4QMa6zhEMb/f800/1743583808.jpeg?s=b70e4aed4f7febc5781988b0c02e8b53a9d06dab",
            "width": 321,
            "height": 428,
            "original_size": true
          },
          {
            "type": "thumb624x428",
            "url": "https://images1.vinted.net/t/04_014b4_EF8wWXjzYV4HMk4QMa6zhEMb/f800/1743583808.jpeg?s=b70e4aed4f7febc5781988b0c02e8b53a9d06dab",
            "width": 468,
            "height": 624,
            "original_size": true
          },
          {
            "type": "thumb364x428",
            "url": "https://images1.vinted.net/t/04_014b4_EF8wWXjzYV4HMk4QMa6zhEMb/f800/1743583808.jpeg?s=b70e4aed4f7febc5781988b0c02e8b53a9d06dab",
            "width": 273,
            "height": 364,
            "original_size": true
          }
        ],
        "high_resolution": {
          "id": "04_014b4_EF8wWXjzYV4HMk4QMa6zhEMb",
          "timestamp": 1743583808,
          "orientation": null
        },
        "is_suspicious": false,
        "full_size_url": "https://images1.vinted.net/tc/04_014b4_EF8wWXjzYV4HMk4QMa6zhEMb/1743583808.jpeg?s=1fe4e6fb5d42b8df2e2653c847fb1dd0730b222b",
        "is_hidden": false,
        "extra": {}
      },
      "favourite_count": 43,
      "is_favourite": false,
      "badge": null,
      "service_fee": {
        "amount": "19.2",
        "currency_code": "EUR"
      },
      "total_item_price": {
        "amount": "389.2",
        "currency_code": "EUR"
      },
      "view_count": 0,
      "size_title": "Taille unique",
      "content_source": "search",
      "status": "Neuf avec étiquette",
      "icon_badges": [],
      "item_box": {
        "first_line": "LEGO",
        "second_line": "Taille unique · Neuf avec étiquette",
        "accessibility_label": "Lego seigneur des anneaux, marque: LEGO, état: Neuf avec étiquette, taille: Taille unique, 370,00 €, 389,20 € Protection acheteurs incluse"
      },
      "search_tracking_params": {
        "score": 1.384511947631836,
        "matched_queries": []
      }
    },
    {
      "id": 6084775549,
      "title": "Lego 10354",
      "price": {
        "amount": "240.0",
        "currency_code": "EUR"
      },
      "is_visible": true,
      "discount": null,
      "brand_title": "LEGO",
      "path": "/items/6084775549-lego-10354",
      "user": {
        "id": 28013590,
        "login": "clem_218",
        "profile_url": "https://www.vinted.fr/member/28013590-clem218",
        "photo": {
          "id": 61959064,
          "width": 96,
          "height": 96,
          "temp_uuid": null,
          "url": "https://images1.vinted.net/t/03_00399_KSMdrvG7aKoioszowzQDCBPq/f800/1625000972.jpeg?s=43199274cba11fb7dad20844b1c4e101ca597b92",
          "dominant_color": "#31abc2",
          "dominant_color_opaque": "#C1E6ED",
          "thumbnails": [
            {
              "type": "thumb310",
              "url": "https://images1.vinted.net/t/03_00399_KSMdrvG7aKoioszowzQDCBPq/310x310/1625000972.jpeg?s=55e2e7cea4c312cca88e818e4ba1624b235ec281",
              "width": 310,
              "height": 310,
              "original_size": null
            },
            {
              "type": "thumb150",
              "url": "https://images1.vinted.net/t/03_00399_KSMdrvG7aKoioszowzQDCBPq/150x150/1625000972.jpeg?s=c3c7820964fe2de0795e69d1c2b0c0a7a030b058",
              "width": 150,
              "height": 150,
              "original_size": null
            },
            {
              "type": "thumb100",
              "url": "https://images1.vinted.net/t/03_00399_KSMdrvG7aKoioszowzQDCBPq/100x100/1625000972.jpeg?s=a93d4b3207b2b78f07488b8d66d6a606fbd3cf98",
              "width": 100,
              "height": 100,
              "original_size": null
            },
            {
              "type": "thumb50",
              "url": "https://images1.vinted.net/t/03_00399_KSMdrvG7aKoioszowzQDCBPq/50x50/1625000972.jpeg?s=16682dfb58920691f171bb4d91e85e4a91b7ed35",
              "width": 50,
              "height": 50,
              "original_size": null
            },
            {
              "type": "thumb20",
              "url": "https://images1.vinted.net/t/03_00399_KSMdrvG7aKoioszowzQDCBPq/20x20/1625000972.jpeg?s=830f7972f8c71a21c1b16b64745a1c7bbea979e0",
              "width": 20,
              "height": 20,
              "original_size": null
            }
          ],
          "is_suspicious": false,
          "orientation": null,
          "high_resolution": {
            "id": "03_00399_KSMdrvG7aKoioszowzQDCBPq",
            "timestamp": 1625000972,
            "orientation": null
          },
          "full_size_url": "https://images1.vinted.net/tc/03_00399_KSMdrvG7aKoioszowzQDCBPq/1625000972.jpeg?s=fe5354de34e6676472db530792e182abab275064",
          "is_hidden": false,
          "extra": {}
        },
        "business": false
      },
      "conversion": null,
      "url": "https://www.vinted.fr/items/6084775549-lego-10354",
      "promoted": false,
      "photo": {
        "id": 24687069598,
        "image_no": 1,
        "width": 600,
        "height": 800,
        "dominant_color": "#656B4B",
        "dominant_color_opaque": "#D1D3C9",
        "url": "https://images1.vinted.net/t/04_0168a_zH3jQ5BsqNw1DrRrbPEKM5vv/f800/1743750655.jpeg?s=f65f1c2fc59951c809fb464109accf8ad711a1ea",
        "is_main": true,
        "thumbnails": [
          {
            "type": "thumb70x100",
            "url": "https://images1.vinted.net/t/04_0168a_zH3jQ5BsqNw1DrRrbPEKM5vv/70x100/1743750655.jpeg?s=27ccd3dc392905afb4c57602b98296abe2231f89",
            "width": 70,
            "height": 100,
            "original_size": null
          },
          {
            "type": "thumb150x210",
            "url": "https://images1.vinted.net/t/04_0168a_zH3jQ5BsqNw1DrRrbPEKM5vv/150x210/1743750655.jpeg?s=1a9038a0f2fc6d48fa52bd218eb246564475fee7",
            "width": 150,
            "height": 210,
            "original_size": null
          },
          {
            "type": "thumb310x430",
            "url": "https://images1.vinted.net/t/04_0168a_zH3jQ5BsqNw1DrRrbPEKM5vv/310x430/1743750655.jpeg?s=538bea038deed67b414c3f41cf00ef2b1c81b877",
            "width": 310,
            "height": 430,
            "original_size": null
          },
          {
            "type": "thumb428x624",
            "url": "https://images1.vinted.net/t/04_0168a_zH3jQ5BsqNw1DrRrbPEKM5vv/f800/1743750655.jpeg?s=f65f1c2fc59951c809fb464109accf8ad711a1ea",
            "width": 321,
            "height": 428,
            "original_size": true
          },
          {
            "type": "thumb624x428",
            "url": "https://images1.vinted.net/t/04_0168a_zH3jQ5BsqNw1DrRrbPEKM5vv/f800/1743750655.jpeg?s=f65f1c2fc59951c809fb464109accf8ad711a1ea",
            "width": 468,
            "height": 624,
            "original_size": true
          },
          {
            "type": "thumb364x428",
            "url": "https://images1.vinted.net/t/04_0168a_zH3jQ5BsqNw1DrRrbPEKM5vv/f800/1743750655.jpeg?s=f65f1c2fc59951c809fb464109accf8ad711a1ea",
            "width": 273,
            "height": 364,
            "original_size": true
          }
        ],
        "high_resolution": {
          "id": "04_0168a_zH3jQ5BsqNw1DrRrbPEKM5vv",
          "timestamp": 1743750655,
          "orientation": null
        },
        "is_suspicious": false,
        "full_size_url": "https://images1.vinted.net/tc/04_0168a_zH3jQ5BsqNw1DrRrbPEKM5vv/1743750655.jpeg?s=362a6ac601e3dd8e54da0d53927ef9c64a16a452",
        "is_hidden": false,
        "extra": {}
      },
      "favourite_count": 3,
      "is_favourite": false,
      "badge": null,
      "service_fee": {
        "amount": "12.7",
        "currency_code": "EUR"
      },
      "total_item_price": {
        "amount": "252.7",
        "currency_code": "EUR"
      },
      "view_count": 0,
      "size_title": "Taille unique",
      "content_source": "search",
      "status": "Neuf avec étiquette",
      "icon_badges": [],
      "item_box": {
        "first_line": "LEGO",
        "second_line": "Taille unique · Neuf avec étiquette",
        "accessibility_label": "Lego 10354, marque: LEGO, état: Neuf avec étiquette, taille: Taille unique, 240,00 €, 252,70 € Protection acheteurs incluse"
      },
      "search_tracking_params": {
        "score": 1.055136442184448,
        "matched_queries": []
      }
    },
    {
      "id": 6081180663,
      "title": "LEGO 10354 - The Shire - The Lord of the Rings",
      "price": {
        "amount": "250.0",
        "currency_code": "EUR"
      },
      "is_visible": true,
      "discount": null,
      "brand_title": "LEGO",
      "path": "/items/6081180663-lego-10354-the-shire-the-lord-of-the-rings",
      "user": {
        "id": 120766433,
        "login": "rhino_3000",
        "profile_url": "https://www.vinted.fr/member/120766433-rhino3000",
        "photo": {
          "id": 226417750,
          "width": 659,
          "height": 800,
          "temp_uuid": null,
          "url": "https://images1.vinted.net/t/04_00fb6_qvvjt4M7JkEv1YoHn6VL71Cw/f800/1737016896.jpeg?s=404b16cfc7ebca85bf5a79451e86c859feea49bd",
          "dominant_color": "#31abc2",
          "dominant_color_opaque": "#C1E6ED",
          "thumbnails": [
            {
              "type": "thumb310",
              "url": "https://images1.vinted.net/t/04_00fb6_qvvjt4M7JkEv1YoHn6VL71Cw/310x310/1737016896.jpeg?s=85373a51e2f3be93bf556c2f93787e2ad1eaf068",
              "width": 310,
              "height": 310,
              "original_size": null
            },
            {
              "type": "thumb150",
              "url": "https://images1.vinted.net/t/04_00fb6_qvvjt4M7JkEv1YoHn6VL71Cw/150x150/1737016896.jpeg?s=61ba81e595a09fe6f0f99492f108fcb04c33f021",
              "width": 150,
              "height": 150,
              "original_size": null
            },
            {
              "type": "thumb100",
              "url": "https://images1.vinted.net/t/04_00fb6_qvvjt4M7JkEv1YoHn6VL71Cw/100x100/1737016896.jpeg?s=320e42b69413ae03a62d11248943eaeb04077b37",
              "width": 100,
              "height": 100,
              "original_size": null
            },
            {
              "type": "thumb50",
              "url": "https://images1.vinted.net/t/04_00fb6_qvvjt4M7JkEv1YoHn6VL71Cw/50x50/1737016896.jpeg?s=0ee051a1db06be75be67692caf55e93d55e89c26",
              "width": 50,
              "height": 50,
              "original_size": null
            },
            {
              "type": "thumb20",
              "url": "https://images1.vinted.net/t/04_00fb6_qvvjt4M7JkEv1YoHn6VL71Cw/20x20/1737016896.jpeg?s=013b4d174e83d695f13b445db935f7651f59ac7e",
              "width": 20,
              "height": 20,
              "original_size": null
            }
          ],
          "is_suspicious": false,
          "orientation": null,
          "high_resolution": {
            "id": "04_00fb6_qvvjt4M7JkEv1YoHn6VL71Cw",
            "timestamp": 1737016896,
            "orientation": null
          },
          "full_size_url": "https://images1.vinted.net/tc/04_00fb6_qvvjt4M7JkEv1YoHn6VL71Cw/1737016896.jpeg?s=a07b05cdfb239fd8274ff4c2f9a9a61d1156cd7a",
          "is_hidden": false,
          "extra": {}
        },
        "business": false
      },
      "conversion": null,
      "url": "https://www.vinted.fr/items/6081180663-lego-10354-the-shire-the-lord-of-the-rings",
      "promoted": false,
      "photo": {
        "id": 24671894045,
        "image_no": 1,
        "width": 793,
        "height": 800,
        "dominant_color": "#4A5338",
        "dominant_color_opaque": "#C9CBC3",
        "url": "https://images1.vinted.net/t/03_00db7_7eJBxGfDgjioBDyUb9uhr9ud/f800/1743680700.jpeg?s=43027fade1fd663b9d54e2b78eb8a87862aa5048",
        "is_main": true,
        "thumbnails": [
          {
            "type": "thumb70x100",
            "url": "https://images1.vinted.net/t/03_00db7_7eJBxGfDgjioBDyUb9uhr9ud/70x100/1743680700.jpeg?s=032d09e25c1bd5d6b5c714634ab3a876c088d6aa",
            "width": 70,
            "height": 100,
            "original_size": null
          },
          {
            "type": "thumb150x210",
            "url": "https://images1.vinted.net/t/03_00db7_7eJBxGfDgjioBDyUb9uhr9ud/150x210/1743680700.jpeg?s=9e4a03557428bb0bc2ee6360d48a87e9ce915910",
            "width": 150,
            "height": 210,
            "original_size": null
          },
          {
            "type": "thumb310x430",
            "url": "https://images1.vinted.net/t/03_00db7_7eJBxGfDgjioBDyUb9uhr9ud/310x430/1743680700.jpeg?s=9d77269ba64442f93ba14ee70e652790522d1318",
            "width": 310,
            "height": 430,
            "original_size": null
          },
          {
            "type": "thumb428x624",
            "url": "https://images1.vinted.net/t/03_00db7_7eJBxGfDgjioBDyUb9uhr9ud/f800/1743680700.jpeg?s=43027fade1fd663b9d54e2b78eb8a87862aa5048",
            "width": 424,
            "height": 428,
            "original_size": true
          },
          {
            "type": "thumb624x428",
            "url": "https://images1.vinted.net/t/03_00db7_7eJBxGfDgjioBDyUb9uhr9ud/f800/1743680700.jpeg?s=43027fade1fd663b9d54e2b78eb8a87862aa5048",
            "width": 618,
            "height": 624,
            "original_size": true
          },
          {
            "type": "thumb364x428",
            "url": "https://images1.vinted.net/t/03_00db7_7eJBxGfDgjioBDyUb9uhr9ud/f800/1743680700.jpeg?s=43027fade1fd663b9d54e2b78eb8a87862aa5048",
            "width": 360,
            "height": 364,
            "original_size": true
          }
        ],
        "high_resolution": {
          "id": "03_00db7_7eJBxGfDgjioBDyUb9uhr9ud",
          "timestamp": 1743680700,
          "orientation": null
        },
        "is_suspicious": false,
        "full_size_url": "https://images1.vinted.net/tc/03_00db7_7eJBxGfDgjioBDyUb9uhr9ud/1743680700.jpeg?s=feb04fd3edaee3d05ade56359388f0ec8b527b2c",
        "is_hidden": false,
        "extra": {}
      },
      "favourite_count": 6,
      "is_favourite": false,
      "badge": null,
      "service_fee": {
        "amount": "13.2",
        "currency_code": "EUR"
      },
      "total_item_price": {
        "amount": "263.2",
        "currency_code": "EUR"
      },
      "view_count": 0,
      "size_title": "Taille unique",
      "content_source": "search",
      "status": "Neuf avec étiquette",
      "icon_badges": [],
      "item_box": {
        "first_line": "LEGO",
        "second_line": "Taille unique · Neuf avec étiquette",
        "accessibility_label": "LEGO 10354 - The Shire - The Lord of the Rings, marque: LEGO, état: Neuf avec étiquette, taille: Taille unique, 250,00 €, 263,20 € Protection acheteurs incluse"
      },
      "search_tracking_params": {
        "score": 0.9069302082061768,
        "matched_queries": []
      }
    },
    {
      "id": 6075951435,
      "title": "Lego The Lord of the Rings: The Shire",
      "price": {
        "amount": "250.0",
        "currency_code": "EUR"
      },
      "is_visible": true,
      "discount": null,
      "brand_title": "LEGO",
      "path": "/items/6075951435-lego-the-lord-of-the-rings-the-shire",
      "user": {
        "id": 64496624,
        "login": "jordicx",
        "profile_url": "https://www.vinted.fr/member/64496624-jordicx",
        "photo": {
          "id": 81290989,
          "width": 629,
          "height": 629,
          "temp_uuid": null,
          "url": "https://images1.vinted.net/t/03_0008e_WQSLoXqkUvjxG2kY17W83Y6b/f800/1644950375.jpeg?s=0d5761ae641314b896b7a64253f2a04474412aa8",
          "dominant_color": "#31abc2",
          "dominant_color_opaque": "#C1E6ED",
          "thumbnails": [
            {
              "type": "thumb310",
              "url": "https://images1.vinted.net/t/03_0008e_WQSLoXqkUvjxG2kY17W83Y6b/310x310/1644950375.jpeg?s=9f86d2f225bd08c875e70f0d4a65d540014ac427",
              "width": 310,
              "height": 310,
              "original_size": null
            },
            {
              "type": "thumb150",
              "url": "https://images1.vinted.net/t/03_0008e_WQSLoXqkUvjxG2kY17W83Y6b/150x150/1644950375.jpeg?s=c7717fc6656be830985c18c35726c73e6a23616c",
              "width": 150,
              "height": 150,
              "original_size": null
            },
            {
              "type": "thumb100",
              "url": "https://images1.vinted.net/t/03_0008e_WQSLoXqkUvjxG2kY17W83Y6b/100x100/1644950375.jpeg?s=74ce9d52c748b66cd2cc5bc6fc86e5deb3586c98",
              "width": 100,
              "height": 100,
              "original_size": null
            },
            {
              "type": "thumb50",
              "url": "https://images1.vinted.net/t/03_0008e_WQSLoXqkUvjxG2kY17W83Y6b/50x50/1644950375.jpeg?s=10eb1fbae90d96058e245c4ef8b7d70b0af40d48",
              "width": 50,
              "height": 50,
              "original_size": null
            },
            {
              "type": "thumb20",
              "url": "https://images1.vinted.net/t/03_0008e_WQSLoXqkUvjxG2kY17W83Y6b/20x20/1644950375.jpeg?s=303dc99731595d224d6ee7fee3dfd6a97519183c",
              "width": 20,
              "height": 20,
              "original_size": null
            }
          ],
          "is_suspicious": false,
          "orientation": null,
          "high_resolution": {
            "id": "03_0008e_WQSLoXqkUvjxG2kY17W83Y6b",
            "timestamp": 1644950375,
            "orientation": null
          },
          "full_size_url": "https://images1.vinted.net/tc/03_0008e_WQSLoXqkUvjxG2kY17W83Y6b/1644950375.jpeg?s=ee25d4897fc7f224c0105d17c9a77d8d551081ff",
          "is_hidden": false,
          "extra": {}
        },
        "business": false
      },
      "conversion": null,
      "url": "https://www.vinted.fr/items/6075951435-lego-the-lord-of-the-rings-the-shire",
      "promoted": false,
      "photo": {
        "id": 24650024463,
        "image_no": 1,
        "width": 800,
        "height": 600,
        "dominant_color": "#676E50",
        "dominant_color_opaque": "#D1D4CB",
        "url": "https://images1.vinted.net/t/03_0264d_MDUi8kz1xZUZPnpkqCYhyDbT/f800/1743595871.jpeg?s=42429938321457c00984cb8811026cd5650209a1",
        "is_main": true,
        "thumbnails": [
          {
            "type": "thumb70x100",
            "url": "https://images1.vinted.net/t/03_0264d_MDUi8kz1xZUZPnpkqCYhyDbT/70x100/1743595871.jpeg?s=2a83199e4aba0dc9f538e511b0385cb0bee20fe3",
            "width": 70,
            "height": 100,
            "original_size": null
          },
          {
            "type": "thumb150x210",
            "url": "https://images1.vinted.net/t/03_0264d_MDUi8kz1xZUZPnpkqCYhyDbT/150x210/1743595871.jpeg?s=7a715dd27fd2fc6d9f5707e3f22d30db879e2f4b",
            "width": 150,
            "height": 210,
            "original_size": null
          },
          {
            "type": "thumb310x430",
            "url": "https://images1.vinted.net/t/03_0264d_MDUi8kz1xZUZPnpkqCYhyDbT/310x430/1743595871.jpeg?s=c65a2421ab8698f172f1d4c0426e870102ee9029",
            "width": 310,
            "height": 430,
            "original_size": null
          },
          {
            "type": "thumb428x624",
            "url": "https://images1.vinted.net/t/03_0264d_MDUi8kz1xZUZPnpkqCYhyDbT/f800/1743595871.jpeg?s=42429938321457c00984cb8811026cd5650209a1",
            "width": 428,
            "height": 321,
            "original_size": true
          },
          {
            "type": "thumb624x428",
            "url": "https://images1.vinted.net/t/03_0264d_MDUi8kz1xZUZPnpkqCYhyDbT/f800/1743595871.jpeg?s=42429938321457c00984cb8811026cd5650209a1",
            "width": 624,
            "height": 468,
            "original_size": true
          },
          {
            "type": "thumb364x428",
            "url": "https://images1.vinted.net/t/03_0264d_MDUi8kz1xZUZPnpkqCYhyDbT/f800/1743595871.jpeg?s=42429938321457c00984cb8811026cd5650209a1",
            "width": 364,
            "height": 273,
            "original_size": true
          }
        ],
        "high_resolution": {
          "id": "03_0264d_MDUi8kz1xZUZPnpkqCYhyDbT",
          "timestamp": 1743595871,
          "orientation": null
        },
        "is_suspicious": false,
        "full_size_url": "https://images1.vinted.net/tc/03_0264d_MDUi8kz1xZUZPnpkqCYhyDbT/1743595871.jpeg?s=acbfc967fdfc0f04c75edde8e3b8e3046a82dd1b",
        "is_hidden": false,
        "extra": {}
      },
      "favourite_count": 9,
      "is_favourite": false,
      "badge": null,
      "service_fee": {
        "amount": "13.2",
        "currency_code": "EUR"
      },
      "total_item_price": {
        "amount": "263.2",
        "currency_code": "EUR"
      },
      "view_count": 0,
      "size_title": "Taille unique",
      "content_source": "search",
      "status": "Très bon état",
      "icon_badges": [],
      "item_box": {
        "first_line": "LEGO",
        "second_line": "Taille unique · Très bon état",
        "accessibility_label": "Lego The Lord of the Rings: The Shire, marque: LEGO, état: Très bon état, taille: Taille unique, 250,00 €, 263,20 € Protection acheteurs incluse"
      },
      "search_tracking_params": {
        "score": 0.7470190525054932,
        "matched_queries": []
      }
    },
    {
      "id": 6074417414,
      "title": "Lego 10354 + Lego 40761",
      "price": {
        "amount": "350.0",
        "currency_code": "EUR"
      },
      "is_visible": true,
      "discount": null,
      "brand_title": "LEGO",
      "path": "/items/6074417414-lego-10354-lego-40761",
      "user": {
        "id": 111496948,
        "login": "andregaddi",
        "profile_url": "https://www.vinted.fr/member/111496948-andregaddi",
        "photo": {
          "id": 235607906,
          "width": 800,
          "height": 600,
          "temp_uuid": null,
          "url": "https://images1.vinted.net/t/03_00e0f_gmaSmwnw8UrFD7akY45Xtk4t/f800/1742449649.jpeg?s=f58eb2220c459cc4d07d242fde0c8effe2182291",
          "dominant_color": "#31abc2",
          "dominant_color_opaque": "#C1E6ED",
          "thumbnails": [
            {
              "type": "thumb310",
              "url": "https://images1.vinted.net/t/03_00e0f_gmaSmwnw8UrFD7akY45Xtk4t/310x310/1742449649.jpeg?s=fce5def98977c86302e1b4bdbc56212f7c66b51c",
              "width": 310,
              "height": 310,
              "original_size": null
            },
            {
              "type": "thumb150",
              "url": "https://images1.vinted.net/t/03_00e0f_gmaSmwnw8UrFD7akY45Xtk4t/150x150/1742449649.jpeg?s=8b0293d9636d09f45d3aa2e7aca5d517bfa78917",
              "width": 150,
              "height": 150,
              "original_size": null
            },
            {
              "type": "thumb100",
              "url": "https://images1.vinted.net/t/03_00e0f_gmaSmwnw8UrFD7akY45Xtk4t/100x100/1742449649.jpeg?s=f107a9d87d8cf0cf12fa3a7d816cfbb67a05789c",
              "width": 100,
              "height": 100,
              "original_size": null
            },
            {
              "type": "thumb50",
              "url": "https://images1.vinted.net/t/03_00e0f_gmaSmwnw8UrFD7akY45Xtk4t/50x50/1742449649.jpeg?s=7fde81a4955bc16bd436d18adea1c46262c937ba",
              "width": 50,
              "height": 50,
              "original_size": null
            },
            {
              "type": "thumb20",
              "url": "https://images1.vinted.net/t/03_00e0f_gmaSmwnw8UrFD7akY45Xtk4t/20x20/1742449649.jpeg?s=b179656e914529d8cc83c3b568e3b3031769fde1",
              "width": 20,
              "height": 20,
              "original_size": null
            }
          ],
          "is_suspicious": false,
          "orientation": null,
          "high_resolution": {
            "id": "03_00e0f_gmaSmwnw8UrFD7akY45Xtk4t",
            "timestamp": 1742449649,
            "orientation": null
          },
          "full_size_url": "https://images1.vinted.net/tc/03_00e0f_gmaSmwnw8UrFD7akY45Xtk4t/1742449649.jpeg?s=8cadfa96d050c219286d6a346c18add417e57611",
          "is_hidden": false,
          "extra": {}
        },
        "business": false
      },
      "conversion": null,
      "url": "https://www.vinted.fr/items/6074417414-lego-10354-lego-40761",
      "promoted": false,
      "photo": {
        "id": 24643658017,
        "image_no": 1,
        "width": 598,
        "height": 800,
        "dominant_color": "#5C5D57",
        "dominant_color_opaque": "#CECECD",
        "url": "https://images1.vinted.net/t/04_00de5_Gays37gtjAAQmZMvkLJndGB5/f800/1743579057.jpeg?s=7462f9e129a84902736658b5046ca389382445d8",
        "is_main": true,
        "thumbnails": [
          {
            "type": "thumb70x100",
            "url": "https://images1.vinted.net/t/04_00de5_Gays37gtjAAQmZMvkLJndGB5/70x100/1743579057.jpeg?s=4efbe9e2ecd8a31ffdca03c323770a5b656dcbc5",
            "width": 70,
            "height": 100,
            "original_size": null
          },
          {
            "type": "thumb150x210",
            "url": "https://images1.vinted.net/t/04_00de5_Gays37gtjAAQmZMvkLJndGB5/150x210/1743579057.jpeg?s=2ccf58a2328991c4163ed4fb90252e271dc0cde0",
            "width": 150,
            "height": 210,
            "original_size": null
          },
          {
            "type": "thumb310x430",
            "url": "https://images1.vinted.net/t/04_00de5_Gays37gtjAAQmZMvkLJndGB5/310x430/1743579057.jpeg?s=fb630a746abff86ac55f2a33bfa4b95a29e1d2a1",
            "width": 310,
            "height": 430,
            "original_size": null
          },
          {
            "type": "thumb428x624",
            "url": "https://images1.vinted.net/t/04_00de5_Gays37gtjAAQmZMvkLJndGB5/f800/1743579057.jpeg?s=7462f9e129a84902736658b5046ca389382445d8",
            "width": 320,
            "height": 428,
            "original_size": true
          },
          {
            "type": "thumb624x428",
            "url": "https://images1.vinted.net/t/04_00de5_Gays37gtjAAQmZMvkLJndGB5/f800/1743579057.jpeg?s=7462f9e129a84902736658b5046ca389382445d8",
            "width": 466,
            "height": 624,
            "original_size": true
          },
          {
            "type": "thumb364x428",
            "url": "https://images1.vinted.net/t/04_00de5_Gays37gtjAAQmZMvkLJndGB5/f800/1743579057.jpeg?s=7462f9e129a84902736658b5046ca389382445d8",
            "width": 272,
            "height": 364,
            "original_size": true
          }
        ],
        "high_resolution": {
          "id": "04_00de5_Gays37gtjAAQmZMvkLJndGB5",
          "timestamp": 1743579057,
          "orientation": null
        },
        "is_suspicious": false,
        "full_size_url": "https://images1.vinted.net/tc/04_00de5_Gays37gtjAAQmZMvkLJndGB5/1743579057.jpeg?s=8ae2afc219b2b1863689e31c2210124e21dd741c",
        "is_hidden": false,
        "extra": {}
      },
      "favourite_count": 14,
      "is_favourite": false,
      "badge": null,
      "service_fee": {
        "amount": "18.2",
        "currency_code": "EUR"
      },
      "total_item_price": {
        "amount": "368.2",
        "currency_code": "EUR"
      },
      "view_count": 0,
      "size_title": "Taille unique",
      "content_source": "search",
      "status": "Neuf avec étiquette",
      "icon_badges": [],
      "item_box": {
        "first_line": "LEGO",
        "second_line": "Taille unique · Neuf avec étiquette",
        "accessibility_label": "Lego 10354 + Lego 40761, marque: LEGO, état: Neuf avec étiquette, taille: Taille unique, 350,00 €, 368,20 € Protection acheteurs incluse"
      },
      "search_tracking_params": {
        "score": 0.6491341590881348,
        "matched_queries": []
      }
    }
  ],
  "dominant_brand": null,
  "search_tracking_params": {
    "search_correlation_id": "0c58e1b6-ee13-4dc6-8ad3-b62cccc0c575",
    "search_session_id": "397b6d26-7a98-492d-b295-34bea4c629d8",
    "global_search_session_id": "9c59b589-5af8-41e4-955b-ce5d5db32ba6"
  },
  "pagination": {
    "current_page": 1,
    "total_pages": 1,
    "total_entries": 11,
    "per_page": 96,
    "time": 1743768414
  },
  "code": 0,
  "setId": "10354"
}